micropattern/__init__.py
micropattern/registry.py
micropattern/remote_configs/__init__.py
micropattern/utils/__init__.py
micropattern/utils/csv.py
micropattern/utils/db.py
micropattern/utils/logger.py
micropattern/utils/mq.py
micropattern/utils/parallel.py
micropattern-0.0.8.dist-info/METADATA
micropattern-0.0.8.dist-info/WHEEL
micropattern-0.0.8.dist-info/top_level.txt
micropattern-0.0.8.dist-info/RECORD
